calculate_readability.py
calculate_readability-0.1.2.dist-info/METADATA
calculate_readability-0.1.2.dist-info/WHEEL
calculate_readability-0.1.2.dist-info/top_level.txt
calculate_readability-0.1.2.dist-info/RECORD
