Metadata-Version: 2.1
Name: calculate-readability
Version: 0.1.2
Summary: Calculate readability by using variable replacement model
Home-page: https://github.com/ShinyaAkagiI/calculate_readability
Author: Shinya Akagi
License: PSF
Requires-Dist: divide-char-type
Requires-Dist: count-syllable
